{
    "keep": {
        "days": true,
        "amount": 1
    },
    "auditLog": "C:\\Users\\rony\\Desktop\\Resume\\university-management\\server\\logs\\winston\\successes\\.f1dd8e2a32172a94fd985e3d73005f26144aa1a1-audit.json",
    "files": [
        {
            "date": 1716063704349,
            "name": "C:\\Users\\rony\\Desktop\\Resume\\university-management\\server\\logs\\winston\\successes\\2024-05-19-02success.log",
            "hash": "468c6b264a90bc332625a90e45885d8d3d90006cb9f1e100dc3f47fb33574dfe"
        }
    ],
    "hashType": "sha256"
}